salmongis/__init__.py
salmongis/common.py
salmongis/salmongis.py
salmongis-0.0.1.dist-info/licenses/LICENSE
salmongis-0.0.1.dist-info/METADATA
salmongis-0.0.1.dist-info/WHEEL
salmongis-0.0.1.dist-info/entry_points.txt
salmongis-0.0.1.dist-info/top_level.txt
salmongis-0.0.1.dist-info/RECORD
